prompt/__init__.py
prompt-0.4.1.dist-info/DESCRIPTION.rst
prompt-0.4.1.dist-info/METADATA
prompt-0.4.1.dist-info/RECORD
prompt-0.4.1.dist-info/WHEEL
prompt-0.4.1.dist-info/metadata.json
prompt-0.4.1.dist-info/top_level.txt
